honcho/__init__.py
honcho/aio.py
honcho/api_types.py
honcho/base.py
honcho/client.py
honcho/conclusions.py
honcho/message.py
honcho/mixins.py
honcho/pagination.py
honcho/peer.py
honcho/session.py
honcho/session_context.py
honcho/types.py
honcho/http/__init__.py
honcho/http/async_client.py
honcho/http/client.py
honcho/http/exceptions.py
honcho/http/routes.py
honcho/utils/__init__.py
honcho/utils/datetime.py
honcho/utils/file_upload.py
honcho/utils/peers.py
honcho/utils/resolve.py
honcho/utils/sse.py
honcho_ai-2.0.0.dist-info/METADATA
honcho_ai-2.0.0.dist-info/WHEEL
honcho_ai-2.0.0.dist-info/top_level.txt
honcho_ai-2.0.0.dist-info/RECORD
