Metadata-Version: 2.4
Name: honcho-ai
Version: 2.0.0
Summary: Official DX Optimized Python SDK for Honcho
Author-email: Plastic Labs <hello@plasticlabs.ai>
License-Expression: Apache-2.0
Project-URL: Homepage, https://github.com/plastic-labs/honcho
Project-URL: Repository, https://github.com/plastic-labs/honcho
Classifier: Typing :: Typed
Classifier: Intended Audience :: Developers
Classifier: Programming Language :: Python :: 3.8
Classifier: Programming Language :: Python :: 3.9
Classifier: Programming Language :: Python :: 3.10
Classifier: Programming Language :: Python :: 3.11
Classifier: Programming Language :: Python :: 3.12
Classifier: Operating System :: OS Independent
Classifier: Operating System :: POSIX
Classifier: Operating System :: MacOS
Classifier: Operating System :: POSIX :: Linux
Classifier: Operating System :: Microsoft :: Windows
Classifier: Topic :: Software Development :: Libraries :: Python Modules
Requires-Python: >=3.8
Requires-Dist: httpx<1,>=0.28.0
Requires-Dist: pydantic<3,>=2.0.0
Requires-Dist: typing-extensions>=4.12.0; python_version < "3.12"
